django_remote_submission/__init__.py
django_remote_submission/admin.py
django_remote_submission/apps.py
django_remote_submission/consumers.py
django_remote_submission/forms.py
django_remote_submission/models.py
django_remote_submission/routing.py
django_remote_submission/serializers.py
django_remote_submission/signals.py
django_remote_submission/tasks.py
django_remote_submission/urls.py
django_remote_submission/views.py
django_remote_submission/migrations/0001_initial.py
django_remote_submission/migrations/__init__.py
django_remote_submission/static/css/django_remote_submission.css
django_remote_submission/static/js/django_remote_submission.js
django_remote_submission/templates/admin/django_remote_submission/submit_to_server.html
django_remote_submission/templates/django_remote_submission/base.html
django_remote_submission/templates/django_remote_submission/job-user-status.html
django_remote_submission/wrapper/__init__.py
django_remote_submission/wrapper/local.py
django_remote_submission/wrapper/remote.py
django_remote_submission-2.1.0.dist-info/METADATA
django_remote_submission-2.1.0.dist-info/RECORD
django_remote_submission-2.1.0.dist-info/WHEEL
django_remote_submission-2.1.0.dist-info/top_level.txt
