Metadata-Version: 1.1
Name: django-remote-submission
Version: 2.1.0
Summary: A Django application to manage long running job submission, including starting the job, saving logs, and storing results.
Home-page: https://github.com/ornl-ndav/django-remote-submission
Author: T. Hobson, M. Doucet and R. M. Ferraz Leal
Author-email: ferrazlealrm@ornl.gov
License: ISCL
Keywords: django-remote-submission
Platform: UNKNOWN
Classifier: Development Status :: 3 - Alpha
Classifier: Framework :: Django
Classifier: Framework :: Django :: 2.0
Classifier: Intended Audience :: Developers
Classifier: License :: OSI Approved :: BSD License
Classifier: Natural Language :: English
Classifier: Programming Language :: Python :: 3.5
Classifier: Programming Language :: Python :: 3.6
